{"target_id": "bokeh-price-hist-container", "root_id": "p14475", "doc": {"version": "3.8.2", "title": "", "config": {"type": "object", "name": "DocumentConfig", "id": "p14516", "attributes": {"notifications": {"type": "object", "name": "Notifications", "id": "p14517"}}}, "roots": [{"type": "object", "name": "Figure", "id": "p14475", "attributes": {"name": "price_hist_fig", "height": 280, "sizing_mode": "stretch_width", "x_range": {"type": "object", "name": "DataRange1d", "id": "p14476"}, "y_range": {"type": "object", "name": "DataRange1d", "id": "p14477"}, "x_scale": {"type": "object", "name": "LogScale", "id": "p14485"}, "y_scale": {"type": "object", "name": "LinearScale", "id": "p14486"}, "title": {"type": "object", "name": "Title", "id": "p14478", "attributes": {"text": "Price Distribution"}}, "outline_line_color": "#e2e8f0", "renderers": [{"type": "object", "name": "GlyphRenderer", "id": "p14507", "attributes": {"data_source": {"type": "object", "name": "ColumnDataSource", "id": "p14472", "attributes": {"selected": {"type": "object", "name": "Selection", "id": "p14473", "attributes": {"indices": [], "line_indices": []}}, "selection_policy": {"type": "object", "name": "UnionRenderers", "id": "p14474"}, "data": {"type": "map", "entries": [["top", [8, 4, 3, 2, 3, 5, 1, 2, 1, 3, 5, 7, 6, 11, 9, 5, 3, 0, 1, 2]], ["left", [383000.0, 406737.6213630899, 431946.4559584967, 458717.68682186835, 487148.14834231196, 517340.67652267776, 549404.4809483176, 583455.5398097694, 619617.0194082066, 658019.719661048, 698802.5472191707, 742113.0179070333, 788107.7903031091, 836953.2323906197, 888826.0233282245, 943913.7925173269, 1002415.7982775733, 1064543.6485853866, 1130522.0664825197, 1200589.7029231982]], ["right", [406737.6213630899, 431946.4559584967, 458717.68682186835, 487148.14834231196, 517340.67652267776, 549404.4809483176, 583455.5398097694, 619617.0194082066, 658019.719661048, 698802.5472191707, 742113.0179070333, 788107.7903031091, 836953.2323906197, 888826.0233282245, 943913.7925173269, 1002415.7982775733, 1064543.6485853866, 1130522.0664825197, 1200589.7029231982, 1275000.0]]]}}}, "view": {"type": "object", "name": "CDSView", "id": "p14508", "attributes": {"filter": {"type": "object", "name": "AllIndices", "id": "p14509"}}}, "glyph": {"type": "object", "name": "Quad", "id": "p14504", "attributes": {"left": {"type": "field", "field": "left"}, "right": {"type": "field", "field": "right"}, "bottom": {"type": "value", "value": 0}, "top": {"type": "field", "field": "top"}, "line_color": {"type": "value", "value": "white"}, "line_alpha": {"type": "value", "value": 0.85}, "fill_color": {"type": "value", "value": "#88419d"}, "fill_alpha": {"type": "value", "value": 0.85}, "hatch_alpha": {"type": "value", "value": 0.85}}}, "nonselection_glyph": {"type": "object", "name": "Quad", "id": "p14505", "attributes": {"left": {"type": "field", "field": "left"}, "right": {"type": "field", "field": "right"}, "bottom": {"type": "value", "value": 0}, "top": {"type": "field", "field": "top"}, "line_color": {"type": "value", "value": "white"}, "line_alpha": {"type": "value", "value": 0.1}, "fill_color": {"type": "value", "value": "#88419d"}, "fill_alpha": {"type": "value", "value": 0.1}, "hatch_alpha": {"type": "value", "value": 0.1}}}, "muted_glyph": {"type": "object", "name": "Quad", "id": "p14506", "attributes": {"left": {"type": "field", "field": "left"}, "right": {"type": "field", "field": "right"}, "bottom": {"type": "value", "value": 0}, "top": {"type": "field", "field": "top"}, "line_color": {"type": "value", "value": "white"}, "line_alpha": {"type": "value", "value": 0.2}, "fill_color": {"type": "value", "value": "#88419d"}, "fill_alpha": {"type": "value", "value": 0.2}, "hatch_alpha": {"type": "value", "value": 0.2}}}}}], "toolbar": {"type": "object", "name": "Toolbar", "id": "p14484", "attributes": {"tools": [{"type": "object", "name": "PanTool", "id": "p14497"}, {"type": "object", "name": "WheelZoomTool", "id": "p14498", "attributes": {"renderers": "auto"}}, {"type": "object", "name": "ResetTool", "id": "p14499"}, {"type": "object", "name": "SaveTool", "id": "p14500"}, {"type": "object", "name": "HoverTool", "id": "p14515", "attributes": {"renderers": "auto", "tooltips": [["Count", "@top"], ["From", "@left{$0.0a}"], ["To", "@right{$0.0a}"]], "sort_by": null}}]}}, "left": [{"type": "object", "name": "LinearAxis", "id": "p14492", "attributes": {"ticker": {"type": "object", "name": "BasicTicker", "id": "p14493", "attributes": {"mantissas": [1, 2, 5]}}, "formatter": {"type": "object", "name": "BasicTickFormatter", "id": "p14494"}, "axis_label": "Listings", "major_label_policy": {"type": "object", "name": "AllLabels", "id": "p14495"}}}], "below": [{"type": "object", "name": "LogAxis", "id": "p14487", "attributes": {"ticker": {"type": "object", "name": "LogTicker", "id": "p14488", "attributes": {"num_minor_ticks": 10, "mantissas": [1, 5]}}, "formatter": {"type": "object", "name": "NumeralTickFormatter", "id": "p14514", "attributes": {"format": "$0.0a"}}, "axis_label": "Sold Price (log scale)", "major_label_policy": {"type": "object", "name": "AllLabels", "id": "p14490"}}}], "center": [{"type": "object", "name": "Grid", "id": "p14491", "attributes": {"axis": {"id": "p14487"}}}, {"type": "object", "name": "Grid", "id": "p14496", "attributes": {"dimension": 1, "axis": {"id": "p14492"}}}, {"type": "object", "name": "Legend", "id": "p14510", "attributes": {"label_text_font_size": "10px", "items": [{"type": "object", "name": "LegendItem", "id": "p14511", "attributes": {"label": {"type": "value", "value": "Neighbourhood"}, "renderers": [{"id": "p14507"}]}}]}}, {"type": "object", "name": "Span", "id": "p14512", "attributes": {"location": 860000.0, "dimension": "height", "line_color": "#9ca3af", "line_width": 2, "line_dash": [6]}}, {"type": "object", "name": "Label", "id": "p14513", "attributes": {"text": "City: $0.86M", "text_color": "#9ca3af", "text_font_size": "10px", "x": 860000.0, "y": 0, "y_units": "screen", "y_offset": 8}}], "background_fill_color": "#fafafa", "border_fill_color": "white"}}]}, "version": "3.8.2"}