{"target_id": "bokeh-languages-pie-container", "root_id": "p15189", "doc": {"version": "3.8.2", "title": "", "config": {"type": "object", "name": "DocumentConfig", "id": "p15229", "attributes": {"notifications": {"type": "object", "name": "Notifications", "id": "p15230"}}}, "roots": [{"type": "object", "name": "Figure", "id": "p15189", "attributes": {"name": "languages_pie_fig", "height": 360, "sizing_mode": "stretch_width", "x_range": {"type": "object", "name": "Range1d", "id": "p15199", "attributes": {"start": -1.4, "end": 2.2}}, "y_range": {"type": "object", "name": "DataRange1d", "id": "p15191"}, "x_scale": {"type": "object", "name": "LinearScale", "id": "p15200"}, "y_scale": {"type": "object", "name": "LinearScale", "id": "p15201"}, "title": {"type": "object", "name": "Title", "id": "p15192", "attributes": {"text": "Languages Spoken at Home"}}, "outline_line_color": "#e2e8f0", "renderers": [{"type": "object", "name": "GlyphRenderer", "id": "p15224", "attributes": {"data_source": {"type": "object", "name": "ColumnDataSource", "id": "p15186", "attributes": {"selected": {"type": "object", "name": "Selection", "id": "p15187", "attributes": {"indices": [], "line_indices": []}}, "selection_policy": {"type": "object", "name": "UnionRenderers", "id": "p15188"}, "data": {"type": "map", "entries": [["language", ["English", "Portuguese", "Cantonese", "Spanish", "Italian", "Mandarin", "Greek", "Other"]], ["count", [9050, 910, 360, 225, 215, 160, 160, 1300]], ["share", [0.7310177705977383, 0.07350565428109855, 0.029079159935379646, 0.018174474959612278, 0.017366720516962843, 0.012924071082390954, 0.012924071082390954, 0.1050080775444265]], ["angle", [4.593120115506887, 0.4618496469736207, 0.1827097504511027, 0.11419359403193917, 0.1091183231860752, 0.08120433353382342, 0.08120433353382342, 0.6597852099623152]], ["color", ["#1f77b4", "#aec7e8", "#ff7f0e", "#ffbb78", "#2ca02c", "#98df8a", "#d62728", "#ff9896"]]]}}}, "view": {"type": "object", "name": "CDSView", "id": "p15225", "attributes": {"filter": {"type": "object", "name": "AllIndices", "id": "p15226"}}}, "glyph": {"type": "object", "name": "AnnularWedge", "id": "p15221", "attributes": {"x": {"type": "value", "value": 0}, "y": {"type": "value", "value": 0}, "inner_radius": {"type": "value", "value": 0.25}, "outer_radius": {"type": "value", "value": 0.6}, "start_angle": {"type": "expr", "expr": {"type": "object", "name": "CumSum", "id": "p15216", "attributes": {"field": "angle", "include_zero": true}}}, "end_angle": {"type": "expr", "expr": {"type": "object", "name": "CumSum", "id": "p15217", "attributes": {"field": "angle"}}}, "line_color": {"type": "value", "value": "white"}, "fill_color": {"type": "field", "field": "color"}}}, "nonselection_glyph": {"type": "object", "name": "AnnularWedge", "id": "p15222", "attributes": {"x": {"type": "value", "value": 0}, "y": {"type": "value", "value": 0}, "inner_radius": {"type": "value", "value": 0.25}, "outer_radius": {"type": "value", "value": 0.6}, "start_angle": {"type": "expr", "expr": {"id": "p15216"}}, "end_angle": {"type": "expr", "expr": {"id": "p15217"}}, "line_color": {"type": "value", "value": "white"}, "line_alpha": {"type": "value", "value": 0.1}, "fill_color": {"type": "field", "field": "color"}, "fill_alpha": {"type": "value", "value": 0.1}, "hatch_alpha": {"type": "value", "value": 0.1}}}, "muted_glyph": {"type": "object", "name": "AnnularWedge", "id": "p15223", "attributes": {"x": {"type": "value", "value": 0}, "y": {"type": "value", "value": 0}, "inner_radius": {"type": "value", "value": 0.25}, "outer_radius": {"type": "value", "value": 0.6}, "start_angle": {"type": "expr", "expr": {"id": "p15216"}}, "end_angle": {"type": "expr", "expr": {"id": "p15217"}}, "line_color": {"type": "value", "value": "white"}, "line_alpha": {"type": "value", "value": 0.2}, "fill_color": {"type": "field", "field": "color"}, "fill_alpha": {"type": "value", "value": 0.2}, "hatch_alpha": {"type": "value", "value": 0.2}}}}}], "toolbar": {"type": "object", "name": "Toolbar", "id": "p15198", "attributes": {"tools": [{"type": "object", "name": "HoverTool", "id": "p15212", "attributes": {"renderers": "auto", "tooltips": [["Language", "@language"], ["Speakers", "@count{0,0}"], ["Share", "@share{0.0%}"]], "sort_by": null}}, {"type": "object", "name": "SaveTool", "id": "p15213"}, {"type": "object", "name": "WheelZoomTool", "id": "p15214", "attributes": {"renderers": "auto"}}, {"type": "object", "name": "ResetTool", "id": "p15215"}]}}, "left": [{"type": "object", "name": "LinearAxis", "id": "p15207", "attributes": {"visible": false, "ticker": {"type": "object", "name": "BasicTicker", "id": "p15208", "attributes": {"mantissas": [1, 2, 5]}}, "formatter": {"type": "object", "name": "BasicTickFormatter", "id": "p15209"}, "major_label_policy": {"type": "object", "name": "AllLabels", "id": "p15210"}}}], "below": [{"type": "object", "name": "LinearAxis", "id": "p15202", "attributes": {"visible": false, "ticker": {"type": "object", "name": "BasicTicker", "id": "p15203", "attributes": {"mantissas": [1, 2, 5]}}, "formatter": {"type": "object", "name": "BasicTickFormatter", "id": "p15204"}, "major_label_policy": {"type": "object", "name": "AllLabels", "id": "p15205"}}}], "center": [{"type": "object", "name": "Grid", "id": "p15206", "attributes": {"axis": {"id": "p15202"}, "grid_line_color": null}}, {"type": "object", "name": "Grid", "id": "p15211", "attributes": {"dimension": 1, "axis": {"id": "p15207"}, "grid_line_color": null}}, {"type": "object", "name": "Legend", "id": "p15227", "attributes": {"location": "center_right", "label_text_font_size": "10px", "spacing": 2, "items": [{"type": "object", "name": "LegendItem", "id": "p15228", "attributes": {"label": {"type": "field", "field": "language"}, "renderers": [{"id": "p15224"}]}}]}}], "background_fill_color": "#fafafa", "border_fill_color": "white"}}]}, "version": "3.8.2"}