{"target_id": "bokeh-price-by-type-container", "root_id": "p86491", "doc": {"version": "3.8.2", "title": "", "config": {"type": "object", "name": "DocumentConfig", "id": "p86542", "attributes": {"notifications": {"type": "object", "name": "Notifications", "id": "p86543"}}}, "roots": [{"type": "object", "name": "Figure", "id": "p86491", "attributes": {"name": "price_by_type_fig", "height": 220, "sizing_mode": "stretch_width", "x_range": {"type": "object", "name": "DataRange1d", "id": "p86493"}, "y_range": {"type": "object", "name": "FactorRange", "id": "p86490", "attributes": {"factors": ["condo apartment", "condo townhouse", "semi-detached", "detached"]}}, "x_scale": {"type": "object", "name": "LinearScale", "id": "p86501"}, "y_scale": {"type": "object", "name": "CategoricalScale", "id": "p86502"}, "title": {"type": "object", "name": "Title", "id": "p86494", "attributes": {"text": "Median Price by House Type"}}, "outline_line_color": "#e2e8f0", "renderers": [{"type": "object", "name": "GlyphRenderer", "id": "p86524", "attributes": {"data_source": {"type": "object", "name": "ColumnDataSource", "id": "p86487", "attributes": {"selected": {"type": "object", "name": "Selection", "id": "p86488", "attributes": {"indices": [], "line_indices": []}}, "selection_policy": {"type": "object", "name": "UnionRenderers", "id": "p86489"}, "data": {"type": "map", "entries": [["house_type", ["condo apartment", "condo townhouse", "semi-detached", "detached"]], ["hood_price", [367500.0, 668750.0, 875000.0, 1085000.0]], ["city_price", [585000.0, 731000.0, 1100000.0, 1260000.0]]]}}}, "view": {"type": "object", "name": "CDSView", "id": "p86525", "attributes": {"filter": {"type": "object", "name": "AllIndices", "id": "p86526"}}}, "glyph": {"type": "object", "name": "HBar", "id": "p86521", "attributes": {"y": {"type": "field", "field": "house_type", "transform": {"type": "object", "name": "Dodge", "id": "p86517", "attributes": {"value": 0.2, "range": {"id": "p86490"}}}}, "height": {"type": "value", "value": 0.35}, "right": {"type": "field", "field": "city_price"}, "line_color": {"type": "value", "value": "#9ca3af"}, "line_alpha": {"type": "value", "value": 0.7}, "fill_color": {"type": "value", "value": "#9ca3af"}, "fill_alpha": {"type": "value", "value": 0.7}, "hatch_color": {"type": "value", "value": "#9ca3af"}, "hatch_alpha": {"type": "value", "value": 0.7}}}, "nonselection_glyph": {"type": "object", "name": "HBar", "id": "p86522", "attributes": {"y": {"type": "field", "field": "house_type", "transform": {"id": "p86517"}}, "height": {"type": "value", "value": 0.35}, "right": {"type": "field", "field": "city_price"}, "line_color": {"type": "value", "value": "#9ca3af"}, "line_alpha": {"type": "value", "value": 0.1}, "fill_color": {"type": "value", "value": "#9ca3af"}, "fill_alpha": {"type": "value", "value": 0.1}, "hatch_color": {"type": "value", "value": "#9ca3af"}, "hatch_alpha": {"type": "value", "value": 0.1}}}, "muted_glyph": {"type": "object", "name": "HBar", "id": "p86523", "attributes": {"y": {"type": "field", "field": "house_type", "transform": {"id": "p86517"}}, "height": {"type": "value", "value": 0.35}, "right": {"type": "field", "field": "city_price"}, "line_color": {"type": "value", "value": "#9ca3af"}, "line_alpha": {"type": "value", "value": 0.2}, "fill_color": {"type": "value", "value": "#9ca3af"}, "fill_alpha": {"type": "value", "value": 0.2}, "hatch_color": {"type": "value", "value": "#9ca3af"}, "hatch_alpha": {"type": "value", "value": 0.2}}}}}, {"type": "object", "name": "GlyphRenderer", "id": "p86536", "attributes": {"data_source": {"id": "p86487"}, "view": {"type": "object", "name": "CDSView", "id": "p86537", "attributes": {"filter": {"type": "object", "name": "AllIndices", "id": "p86538"}}}, "glyph": {"type": "object", "name": "HBar", "id": "p86533", "attributes": {"y": {"type": "field", "field": "house_type", "transform": {"type": "object", "name": "Dodge", "id": "p86529", "attributes": {"value": -0.2, "range": {"id": "p86490"}}}}, "height": {"type": "value", "value": 0.35}, "right": {"type": "field", "field": "hood_price"}, "line_color": {"type": "value", "value": "#88419d"}, "line_alpha": {"type": "value", "value": 0.85}, "fill_color": {"type": "value", "value": "#88419d"}, "fill_alpha": {"type": "value", "value": 0.85}, "hatch_color": {"type": "value", "value": "#88419d"}, "hatch_alpha": {"type": "value", "value": 0.85}}}, "nonselection_glyph": {"type": "object", "name": "HBar", "id": "p86534", "attributes": {"y": {"type": "field", "field": "house_type", "transform": {"id": "p86529"}}, "height": {"type": "value", "value": 0.35}, "right": {"type": "field", "field": "hood_price"}, "line_color": {"type": "value", "value": "#88419d"}, "line_alpha": {"type": "value", "value": 0.1}, "fill_color": {"type": "value", "value": "#88419d"}, "fill_alpha": {"type": "value", "value": 0.1}, "hatch_color": {"type": "value", "value": "#88419d"}, "hatch_alpha": {"type": "value", "value": 0.1}}}, "muted_glyph": {"type": "object", "name": "HBar", "id": "p86535", "attributes": {"y": {"type": "field", "field": "house_type", "transform": {"id": "p86529"}}, "height": {"type": "value", "value": 0.35}, "right": {"type": "field", "field": "hood_price"}, "line_color": {"type": "value", "value": "#88419d"}, "line_alpha": {"type": "value", "value": 0.2}, "fill_color": {"type": "value", "value": "#88419d"}, "fill_alpha": {"type": "value", "value": 0.2}, "hatch_color": {"type": "value", "value": "#88419d"}, "hatch_alpha": {"type": "value", "value": 0.2}}}}}], "toolbar": {"type": "object", "name": "Toolbar", "id": "p86500", "attributes": {"tools": [{"type": "object", "name": "PanTool", "id": "p86513"}, {"type": "object", "name": "WheelZoomTool", "id": "p86514", "attributes": {"renderers": "auto"}}, {"type": "object", "name": "ResetTool", "id": "p86515"}, {"type": "object", "name": "SaveTool", "id": "p86516"}, {"type": "object", "name": "HoverTool", "id": "p86541", "attributes": {"renderers": "auto", "tooltips": [["Type", "@house_type"], ["Neighbourhood", "@hood_price{$0.0a}"], ["City median", "@city_price{$0.0a}"]], "sort_by": null}}]}}, "left": [{"type": "object", "name": "CategoricalAxis", "id": "p86508", "attributes": {"ticker": {"type": "object", "name": "CategoricalTicker", "id": "p86509"}, "formatter": {"type": "object", "name": "CategoricalTickFormatter", "id": "p86510"}, "major_label_policy": {"type": "object", "name": "AllLabels", "id": "p86511"}}}], "below": [{"type": "object", "name": "LinearAxis", "id": "p86503", "attributes": {"ticker": {"type": "object", "name": "BasicTicker", "id": "p86504", "attributes": {"mantissas": [1, 2, 5]}}, "formatter": {"type": "object", "name": "NumeralTickFormatter", "id": "p86540", "attributes": {"format": "$0.0a"}}, "axis_label": "Median Sold Price", "major_label_policy": {"type": "object", "name": "AllLabels", "id": "p86506"}}}], "center": [{"type": "object", "name": "Grid", "id": "p86507", "attributes": {"axis": {"id": "p86503"}}}, {"type": "object", "name": "Grid", "id": "p86512", "attributes": {"dimension": 1, "axis": {"id": "p86508"}}}, {"type": "object", "name": "Legend", "id": "p86527", "attributes": {"location": "bottom_right", "label_text_font_size": "10px", "items": [{"type": "object", "name": "LegendItem", "id": "p86528", "attributes": {"label": {"type": "value", "value": "City median"}, "renderers": [{"id": "p86524"}]}}, {"type": "object", "name": "LegendItem", "id": "p86539", "attributes": {"label": {"type": "value", "value": "Neighbourhood"}, "renderers": [{"id": "p86536"}]}}]}}], "background_fill_color": "#fafafa", "border_fill_color": "white"}}]}, "version": "3.8.2"}