{"target_id": "bokeh-languages-pie-container", "root_id": "p27021", "doc": {"version": "3.8.2", "title": "", "config": {"type": "object", "name": "DocumentConfig", "id": "p27061", "attributes": {"notifications": {"type": "object", "name": "Notifications", "id": "p27062"}}}, "roots": [{"type": "object", "name": "Figure", "id": "p27021", "attributes": {"name": "languages_pie_fig", "height": 360, "sizing_mode": "stretch_width", "x_range": {"type": "object", "name": "Range1d", "id": "p27031", "attributes": {"start": -1.4, "end": 2.2}}, "y_range": {"type": "object", "name": "DataRange1d", "id": "p27023"}, "x_scale": {"type": "object", "name": "LinearScale", "id": "p27032"}, "y_scale": {"type": "object", "name": "LinearScale", "id": "p27033"}, "title": {"type": "object", "name": "Title", "id": "p27024", "attributes": {"text": "Languages Spoken at Home"}}, "outline_line_color": "#e2e8f0", "renderers": [{"type": "object", "name": "GlyphRenderer", "id": "p27056", "attributes": {"data_source": {"type": "object", "name": "ColumnDataSource", "id": "p27018", "attributes": {"selected": {"type": "object", "name": "Selection", "id": "p27019", "attributes": {"indices": [], "line_indices": []}}, "selection_policy": {"type": "object", "name": "UnionRenderers", "id": "p27020"}, "data": {"type": "map", "entries": [["language", ["English", "Spanish", "Russian", "Portuguese", "Polish", "Mandarin", "Arabic", "Other"]], ["count", [16445, 555, 370, 325, 310, 265, 235, 4095]], ["share", [0.7276548672566372, 0.024557522123893807, 0.016371681415929203, 0.014380530973451327, 0.013716814159292035, 0.011725663716814159, 0.010398230088495575, 0.18119469026548674]], ["angle", [4.571990370644615, 0.1542994621895872, 0.10286630812639146, 0.09035554092183033, 0.08618528518697663, 0.0736745179824155, 0.06533400651270808, 1.1384798156150622]], ["color", ["#1f77b4", "#aec7e8", "#ff7f0e", "#ffbb78", "#2ca02c", "#98df8a", "#d62728", "#ff9896"]]]}}}, "view": {"type": "object", "name": "CDSView", "id": "p27057", "attributes": {"filter": {"type": "object", "name": "AllIndices", "id": "p27058"}}}, "glyph": {"type": "object", "name": "AnnularWedge", "id": "p27053", "attributes": {"x": {"type": "value", "value": 0}, "y": {"type": "value", "value": 0}, "inner_radius": {"type": "value", "value": 0.25}, "outer_radius": {"type": "value", "value": 0.6}, "start_angle": {"type": "expr", "expr": {"type": "object", "name": "CumSum", "id": "p27048", "attributes": {"field": "angle", "include_zero": true}}}, "end_angle": {"type": "expr", "expr": {"type": "object", "name": "CumSum", "id": "p27049", "attributes": {"field": "angle"}}}, "line_color": {"type": "value", "value": "white"}, "fill_color": {"type": "field", "field": "color"}}}, "nonselection_glyph": {"type": "object", "name": "AnnularWedge", "id": "p27054", "attributes": {"x": {"type": "value", "value": 0}, "y": {"type": "value", "value": 0}, "inner_radius": {"type": "value", "value": 0.25}, "outer_radius": {"type": "value", "value": 0.6}, "start_angle": {"type": "expr", "expr": {"id": "p27048"}}, "end_angle": {"type": "expr", "expr": {"id": "p27049"}}, "line_color": {"type": "value", "value": "white"}, "line_alpha": {"type": "value", "value": 0.1}, "fill_color": {"type": "field", "field": "color"}, "fill_alpha": {"type": "value", "value": 0.1}, "hatch_alpha": {"type": "value", "value": 0.1}}}, "muted_glyph": {"type": "object", "name": "AnnularWedge", "id": "p27055", "attributes": {"x": {"type": "value", "value": 0}, "y": {"type": "value", "value": 0}, "inner_radius": {"type": "value", "value": 0.25}, "outer_radius": {"type": "value", "value": 0.6}, "start_angle": {"type": "expr", "expr": {"id": "p27048"}}, "end_angle": {"type": "expr", "expr": {"id": "p27049"}}, "line_color": {"type": "value", "value": "white"}, "line_alpha": {"type": "value", "value": 0.2}, "fill_color": {"type": "field", "field": "color"}, "fill_alpha": {"type": "value", "value": 0.2}, "hatch_alpha": {"type": "value", "value": 0.2}}}}}], "toolbar": {"type": "object", "name": "Toolbar", "id": "p27030", "attributes": {"tools": [{"type": "object", "name": "HoverTool", "id": "p27044", "attributes": {"renderers": "auto", "tooltips": [["Language", "@language"], ["Speakers", "@count{0,0}"], ["Share", "@share{0.0%}"]], "sort_by": null}}, {"type": "object", "name": "SaveTool", "id": "p27045"}, {"type": "object", "name": "WheelZoomTool", "id": "p27046", "attributes": {"renderers": "auto"}}, {"type": "object", "name": "ResetTool", "id": "p27047"}]}}, "left": [{"type": "object", "name": "LinearAxis", "id": "p27039", "attributes": {"visible": false, "ticker": {"type": "object", "name": "BasicTicker", "id": "p27040", "attributes": {"mantissas": [1, 2, 5]}}, "formatter": {"type": "object", "name": "BasicTickFormatter", "id": "p27041"}, "major_label_policy": {"type": "object", "name": "AllLabels", "id": "p27042"}}}], "below": [{"type": "object", "name": "LinearAxis", "id": "p27034", "attributes": {"visible": false, "ticker": {"type": "object", "name": "BasicTicker", "id": "p27035", "attributes": {"mantissas": [1, 2, 5]}}, "formatter": {"type": "object", "name": "BasicTickFormatter", "id": "p27036"}, "major_label_policy": {"type": "object", "name": "AllLabels", "id": "p27037"}}}], "center": [{"type": "object", "name": "Grid", "id": "p27038", "attributes": {"axis": {"id": "p27034"}, "grid_line_color": null}}, {"type": "object", "name": "Grid", "id": "p27043", "attributes": {"dimension": 1, "axis": {"id": "p27039"}, "grid_line_color": null}}, {"type": "object", "name": "Legend", "id": "p27059", "attributes": {"location": "center_right", "label_text_font_size": "10px", "spacing": 2, "items": [{"type": "object", "name": "LegendItem", "id": "p27060", "attributes": {"label": {"type": "field", "field": "language"}, "renderers": [{"id": "p27056"}]}}]}}], "background_fill_color": "#fafafa", "border_fill_color": "white"}}]}, "version": "3.8.2"}