{"target_id": "bokeh-price-hist-container", "root_id": "p170831", "doc": {"version": "3.8.2", "title": "", "config": {"type": "object", "name": "DocumentConfig", "id": "p170872", "attributes": {"notifications": {"type": "object", "name": "Notifications", "id": "p170873"}}}, "roots": [{"type": "object", "name": "Figure", "id": "p170831", "attributes": {"name": "price_hist_fig", "height": 280, "sizing_mode": "stretch_width", "x_range": {"type": "object", "name": "DataRange1d", "id": "p170832"}, "y_range": {"type": "object", "name": "DataRange1d", "id": "p170833"}, "x_scale": {"type": "object", "name": "LogScale", "id": "p170841"}, "y_scale": {"type": "object", "name": "LinearScale", "id": "p170842"}, "title": {"type": "object", "name": "Title", "id": "p170834", "attributes": {"text": "Price Distribution"}}, "outline_line_color": "#e2e8f0", "renderers": [{"type": "object", "name": "GlyphRenderer", "id": "p170863", "attributes": {"data_source": {"type": "object", "name": "ColumnDataSource", "id": "p170828", "attributes": {"selected": {"type": "object", "name": "Selection", "id": "p170829", "attributes": {"indices": [], "line_indices": []}}, "selection_policy": {"type": "object", "name": "UnionRenderers", "id": "p170830"}, "data": {"type": "map", "entries": [["top", [1, 0, 0, 0, 0, 0, 0, 0, 0, 0, 0, 0, 0, 0, 0, 0, 6, 21, 15, 7]], ["left", [1800.0, 2499.59345213117, 3471.0930144094596, 4820.178539197851, 6693.603730378965, 9295.1600308978, 12907.845083190838, 17924.647250592985, 24891.294944079535, 34565.6210318261, 48000.000000000044, 66655.82539016467, 92562.48038425225, 128538.09437860922, 178496.09947677242, 247870.9341572749, 344209.202218423, 477990.59334914625, 663767.8651754543, 921749.8941820294]], ["right", [2499.59345213117, 3471.0930144094596, 4820.178539197851, 6693.603730378965, 9295.1600308978, 12907.845083190838, 17924.647250592985, 24891.294944079535, 34565.6210318261, 48000.000000000044, 66655.82539016467, 92562.48038425225, 128538.09437860922, 178496.09947677242, 247870.9341572749, 344209.202218423, 477990.59334914625, 663767.8651754543, 921749.8941820294, 1280000.0]]]}}}, "view": {"type": "object", "name": "CDSView", "id": "p170864", "attributes": {"filter": {"type": "object", "name": "AllIndices", "id": "p170865"}}}, "glyph": {"type": "object", "name": "Quad", "id": "p170860", "attributes": {"left": {"type": "field", "field": "left"}, "right": {"type": "field", "field": "right"}, "bottom": {"type": "value", "value": 0}, "top": {"type": "field", "field": "top"}, "line_color": {"type": "value", "value": "white"}, "line_alpha": {"type": "value", "value": 0.85}, "fill_color": {"type": "value", "value": "#88419d"}, "fill_alpha": {"type": "value", "value": 0.85}, "hatch_alpha": {"type": "value", "value": 0.85}}}, "nonselection_glyph": {"type": "object", "name": "Quad", "id": "p170861", "attributes": {"left": {"type": "field", "field": "left"}, "right": {"type": "field", "field": "right"}, "bottom": {"type": "value", "value": 0}, "top": {"type": "field", "field": "top"}, "line_color": {"type": "value", "value": "white"}, "line_alpha": {"type": "value", "value": 0.1}, "fill_color": {"type": "value", "value": "#88419d"}, "fill_alpha": {"type": "value", "value": 0.1}, "hatch_alpha": {"type": "value", "value": 0.1}}}, "muted_glyph": {"type": "object", "name": "Quad", "id": "p170862", "attributes": {"left": {"type": "field", "field": "left"}, "right": {"type": "field", "field": "right"}, "bottom": {"type": "value", "value": 0}, "top": {"type": "field", "field": "top"}, "line_color": {"type": "value", "value": "white"}, "line_alpha": {"type": "value", "value": 0.2}, "fill_color": {"type": "value", "value": "#88419d"}, "fill_alpha": {"type": "value", "value": 0.2}, "hatch_alpha": {"type": "value", "value": 0.2}}}}}], "toolbar": {"type": "object", "name": "Toolbar", "id": "p170840", "attributes": {"tools": [{"type": "object", "name": "PanTool", "id": "p170853"}, {"type": "object", "name": "WheelZoomTool", "id": "p170854", "attributes": {"renderers": "auto"}}, {"type": "object", "name": "ResetTool", "id": "p170855"}, {"type": "object", "name": "SaveTool", "id": "p170856"}, {"type": "object", "name": "HoverTool", "id": "p170871", "attributes": {"renderers": "auto", "tooltips": [["Count", "@top"], ["From", "@left{$0.0a}"], ["To", "@right{$0.0a}"]], "sort_by": null}}]}}, "left": [{"type": "object", "name": "LinearAxis", "id": "p170848", "attributes": {"ticker": {"type": "object", "name": "BasicTicker", "id": "p170849", "attributes": {"mantissas": [1, 2, 5]}}, "formatter": {"type": "object", "name": "BasicTickFormatter", "id": "p170850"}, "axis_label": "Listings", "major_label_policy": {"type": "object", "name": "AllLabels", "id": "p170851"}}}], "below": [{"type": "object", "name": "LogAxis", "id": "p170843", "attributes": {"ticker": {"type": "object", "name": "LogTicker", "id": "p170844", "attributes": {"num_minor_ticks": 10, "mantissas": [1, 5]}}, "formatter": {"type": "object", "name": "NumeralTickFormatter", "id": "p170870", "attributes": {"format": "$0.0a"}}, "axis_label": "Sold Price (log scale)", "major_label_policy": {"type": "object", "name": "AllLabels", "id": "p170846"}}}], "center": [{"type": "object", "name": "Grid", "id": "p170847", "attributes": {"axis": {"id": "p170843"}}}, {"type": "object", "name": "Grid", "id": "p170852", "attributes": {"dimension": 1, "axis": {"id": "p170848"}}}, {"type": "object", "name": "Legend", "id": "p170866", "attributes": {"label_text_font_size": "10px", "items": [{"type": "object", "name": "LegendItem", "id": "p170867", "attributes": {"label": {"type": "value", "value": "Neighbourhood"}, "renderers": [{"id": "p170863"}]}}]}}, {"type": "object", "name": "Span", "id": "p170868", "attributes": {"location": 860000.0, "dimension": "height", "line_color": "#9ca3af", "line_width": 2, "line_dash": [6]}}, {"type": "object", "name": "Label", "id": "p170869", "attributes": {"text": "City: $0.86M", "text_color": "#9ca3af", "text_font_size": "10px", "x": 860000.0, "y": 0, "y_units": "screen", "y_offset": 8}}], "background_fill_color": "#fafafa", "border_fill_color": "white"}}]}, "version": "3.8.2"}